Contabelib/__init__.py
Contabelib/calcular_balanco.py
Contabelib/calcular_rescisao.py
Contabelib/exportar_pdf.py
Contabelib/grafico.py
Contabelib-0.0.1.dist-info/METADATA
Contabelib-0.0.1.dist-info/WHEEL
Contabelib-0.0.1.dist-info/top_level.txt
Contabelib-0.0.1.dist-info/RECORD
