Metadata-Version: 2.1
Name: Contabelib
Version: 0.0.1
Summary: Pacote de teste
Author: crisly
Author-email: crislymaria21@gmail.com
Keywords: python,contablib
Classifier: Development Status :: 3 - Alpha
Requires-Dist: numpy
Requires-Dist: matplotlib
Requires-Dist: fpdf
